mega_drive/__init__.py
mega_drive/app_setting.py
mega_drive/apps.py
mega_drive/mega.py
mega_drive/storage.py
mega_drive/utils.py
django_mega_drive-1.6.dist-info/LICENSE
django_mega_drive-1.6.dist-info/METADATA
django_mega_drive-1.6.dist-info/WHEEL
django_mega_drive-1.6.dist-info/top_level.txt
django_mega_drive-1.6.dist-info/RECORD
